{"user":{"displayName":"Alin Aioanei"},"short-term interests":[{"interest":"music \"GrasuXXL\""},{"interest":"music \"HaarpCord\""},{"interest":"music \"PerAspera\""},{"interest":"group \"Ia?i - Distrac?ie\""}],"long-term interests":[{"interest":"education \"Liceul de Informatica \\\"Grigore Moisil\\\" Iasi\""},{"interest":"group \"Fotbal - FII\""},{"interest":"group \"Fan Victor OP\""},{"interest":"group \"Dragos e tare!\""},{"interest":"sport \"Stifler\""},{"interest":"group \"FII(2013-2016)\""},{"interest":"group \"Coduri si criptografie(2014-2015)\""},{"interest":"event \"HANGARIADA FESTIVAL\""},{"interest":"sport \"Fnatic\""},{"interest":"group \"PSGBD\""},{"interest":"group \"Cel mai mare grup de Tumblr din Romania\""},{"interest":"music \"C2C\""},{"interest":"group \"LAN Party FII\""},{"interest":"group \"Liceul de Informatica \\\"Grigore Moisil\\\" Iasi\""},{"interest":"music \"Linkin Park\""},{"interest":"group \"FII\""},{"interest":"group \"Dacia Reloaded\""},{"interest":"group \"Sa le luam banii!\""},{"interest":"group \"COROCAIESTI-SATUL MEU DE BASTINA\""},{"interest":"group \"FII A5\""},{"interest":"music \"dram & bass\""},{"interest":"group \"Fotbal la 26\""},{"interest":"group \"League of Legends Romania (fara agramati)\""},{"interest":"group \"12E -LI1S\""},{"interest":"group \"Wildwood 2015\""},{"interest":"music \"Stereodose\""},{"interest":"group \"12  E - LIIS\""},{"interest":"group \"Zi-mi un film bun!\""},{"interest":"group \"Dacia reloaded VIP\""},{"interest":"music \"GuessWho\""},{"interest":"music \"Red Hot Chili Peppers\""},{"interest":"music \"Eminem\""},{"interest":"group \"Olimpiada Bla bla\""},{"interest":"music \"CTC\""},{"interest":"music \"Deliric\""},{"interest":"group \"Work and Travel USA\""}]}